MANIFEST.in
requirements.txt
sd
setup.py
sd_cli.egg-info/PKG-INFO
sd_cli.egg-info/SOURCES.txt
sd_cli.egg-info/dependency_links.txt
sd_cli.egg-info/top_level.txt
sdclient/__init__.py