Metadata-Version: 1.0
Name: sd-cli
Version: 0.1
Summary: Command line interface for Server Density
Home-page: https://github.com/bahadir/sd-cli
Author: Bahadır Kandemir
Author-email: kandemir@gmail.com
License: UNKNOWN
Platform: UNKNOWN
